emojisearcher/__init__.py
emojisearcher/preferences.py
emojisearcher/script.py
emojisearcher-0.6.0.dist-info/LICENSE
emojisearcher-0.6.0.dist-info/WHEEL
emojisearcher-0.6.0.dist-info/METADATA
emojisearcher-0.6.0.dist-info/RECORD
