Metadata-Version: 2.1
Name: emojisearcher
Version: 0.6.0
Summary: Look up emojis by text and copy them to the clipboard.
Author-email: Bob Belderbos <bob@pybit.es>
Requires-Python: >=3.10
Classifier: License :: OSI Approved :: MIT License
Requires-Dist: pyperclip >=1.8.2
Requires-Dist: rich >=12.3.0
Requires-Dist: pytest ; extra == "test"
Project-URL: Source, https://github.com/bbelderbos/emojisearcher
Provides-Extra: test
